panel_jstree/__init__.py
panel_jstree/bokeh.ext.json
panel_jstree/index.ts
panel_jstree/package-lock.json
panel_jstree/package.json
panel_jstree/py.typed
panel_jstree/tsconfig.json
panel_jstree/bokeh_extensions/__init__.py
panel_jstree/bokeh_extensions/index.ts
panel_jstree/bokeh_extensions/jstree.py
panel_jstree/bokeh_extensions/jstree.ts
panel_jstree/bokeh_extensions/layout.py
panel_jstree/bokeh_extensions/layout.ts
panel_jstree/dist/panel_jstree.js
panel_jstree/dist/panel_jstree.js.map
panel_jstree/dist/panel_jstree.json
panel_jstree/dist/panel_jstree.min.js
panel_jstree/dist/lib/index.d.ts
panel_jstree/dist/lib/index.js
panel_jstree/dist/lib/index.js.map
panel_jstree/dist/lib/bokeh_extensions/index.d.ts
panel_jstree/dist/lib/bokeh_extensions/index.js
panel_jstree/dist/lib/bokeh_extensions/index.js.map
panel_jstree/dist/lib/bokeh_extensions/jstree.d.ts
panel_jstree/dist/lib/bokeh_extensions/jstree.js
panel_jstree/dist/lib/bokeh_extensions/jstree.js.map
panel_jstree/dist/lib/bokeh_extensions/layout.d.ts
panel_jstree/dist/lib/bokeh_extensions/layout.js
panel_jstree/dist/lib/bokeh_extensions/layout.js.map
panel_jstree/widgets/__init__.py
panel_jstree/widgets/jstree.py
panel_jstree-0.3.5.dist-info/LICENSE
panel_jstree-0.3.5.dist-info/METADATA
panel_jstree-0.3.5.dist-info/WHEEL
panel_jstree-0.3.5.dist-info/top_level.txt
panel_jstree-0.3.5.dist-info/RECORD
