Metadata-Version: 2.1
Name: panel-jstree
Version: 0.3.5
Summary: panel-jstree is a wrapper python wrapper around the javascript library jstree for use in panel. This allows for JSON-like representations of tree data. One very useful implementation provided is a server-side file browser.
Author: madeline-scyphers
License: MIT License
Project-URL: repository, https://github.com/madeline-scyphers/panel-jstree
Keywords: python,holoviz,panel,dataviz,dataapp,dashboard,datascience,analytics
Classifier: License :: OSI Approved :: MIT License
Classifier: Development Status :: 3 - Alpha
Classifier: Programming Language :: Python :: 3
Classifier: Programming Language :: Python :: 3.8
Classifier: Programming Language :: Python :: 3.9
Classifier: Programming Language :: Python :: 3.10
Classifier: Programming Language :: Python :: 3.11
Classifier: Operating System :: OS Independent
Classifier: Intended Audience :: Developers
Classifier: Intended Audience :: Education
Classifier: Intended Audience :: Financial and Insurance Industry
Classifier: Intended Audience :: Healthcare Industry
Classifier: Intended Audience :: Information Technology
Classifier: Intended Audience :: Legal Industry
Classifier: Intended Audience :: Other Audience
Classifier: Intended Audience :: Science/Research
Classifier: Natural Language :: English
Classifier: Topic :: Office/Business :: Financial
Classifier: Topic :: Office/Business
Classifier: Topic :: Scientific/Engineering :: Information Analysis
Classifier: Topic :: Scientific/Engineering :: Visualization
Classifier: Topic :: Scientific/Engineering
Classifier: Topic :: Software Development :: Libraries
Requires-Python: >=3.8
License-File: LICENSE
Requires-Dist: panel >1.3
Provides-Extra: dev
Requires-Dist: pytest ; extra == 'dev'
Requires-Dist: black ; extra == 'dev'
Requires-Dist: isort ; extra == 'dev'
Provides-Extra: examples
Requires-Dist: notebook ; extra == 'examples'
